<?xml version="1.0" encoding="UTF-8" standalone="no"?>
<rdf:RDF xmlns:rdf="http://www.w3.org/1999/02/22-rdf-syntax-ns#" 
	xmlns:owl="http://www.w3.org/2002/07/owl#" 
    xmlns:rdfs="http://www.w3.org/2000/01/rdf-schema#" 
    xmlns:histo="https://pathoml-1308125782.cos.ap-chengdu.myqcloud.com/PathoML.owl#"
    xmlns:xsd="http://www.w3.org/2001/XMLSchema#">
	<owl:Ontology rdf:about="">
        <owl:imports rdf:resource="https://pathoml-1308125782.cos.ap-chengdu.myqcloud.com/PathoML.owl"/>
    </owl:Ontology>

    <!--Phenotype -->
    <histo:Architectural_Pattern rdf:ID="Glandular_Pattern1"> 
        <histo:displayName rdf:datatype="http://www.w3.org/2001/XMLSchema#string">Glandular Pattern</histo:displayName>
		<histo:hasXref rdf:resource="#UnificationXref_Glandular_Pattern"/>
    </histo:Architectural_Pattern>
    <histo:Architectural_Pattern rdf:ID="Glandular_Pattern2"> 
        <histo:displayName rdf:datatype="http://www.w3.org/2001/XMLSchema#string">Glandular Pattern</histo:displayName>
		<histo:hasXref rdf:resource="#UnificationXref_Glandular_Pattern"/>
    </histo:Architectural_Pattern>
    <histo:Architectural_Pattern rdf:ID="Glandular_Pattern3"> 
        <histo:displayName rdf:datatype="http://www.w3.org/2001/XMLSchema#string">Glandular Pattern</histo:displayName>
		<histo:hasXref rdf:resource="#UnificationXref_Glandular_Pattern"/>
    </histo:Architectural_Pattern>
    <histo:Architectural_Pattern rdf:ID="Glandular_Pattern4"> 
        <histo:present_Entity rdf:resource="#Tumor1"/>
        <histo:displayName rdf:datatype="http://www.w3.org/2001/XMLSchema#string">Glandular Pattern with Apoptic Bodies</histo:displayName>
		<histo:hasXref rdf:resource="#UnificationXref_Glandular_Pattern_with_Apoptic_Bodies"/>
    </histo:Architectural_Pattern>
    <histo:Architectural_Pattern rdf:ID="Glandular_Pattern5"> 
        <histo:present_Entity rdf:resource="#Tumor2"/>
        <histo:displayName rdf:datatype="http://www.w3.org/2001/XMLSchema#string">Glandular Pattern with Apical Mitoses</histo:displayName>
		<histo:hasXref rdf:resource="#UnificationXref_Glandular_Pattern_with_Apical_Mitoses"/>
    </histo:Architectural_Pattern>
    <histo:Architectural_Pattern rdf:ID="Glandular_Pattern6"> 
        <histo:displayName rdf:datatype="http://www.w3.org/2001/XMLSchema#string">Glandular Pattern</histo:displayName>
		<histo:hasXref rdf:resource="#UnificationXref_Glandular_Pattern"/>
    </histo:Architectural_Pattern>
    <histo:Architectural_Pattern rdf:ID="Glandular_Pattern7"> 
        <histo:displayName rdf:datatype="http://www.w3.org/2001/XMLSchema#string">Glandular Pattern</histo:displayName>
		<histo:hasXref rdf:resource="#UnificationXref_Glandular_Pattern"/>
    </histo:Architectural_Pattern>
    <histo:Quantitative_Metric rdf:ID="Quantitative_Metric1"> 
        <histo:hasXref rdf:resource="#UnificationXref_Percent_of_Tumor_Having_Cells_with_Mucinous_Cytoplasm"/>
        <histo:displayName rdf:datatype="http://www.w3.org/2001/XMLSchema#string">Percent of Tumor Having Cells with Mucinous Cytoplasm</histo:displayName>
		<histo:hasValue rdf:datatype="http://www.w3.org/2001/XMLSchema#float">0.4</histo:hasValue>
    </histo:Quantitative_Metric>

    
    <!--Tumor Parenchyma Stroma-->
	<histo:Tumor rdf:ID="Tumor1">
		<histo:hasComponent rdf:resource="#Parenchyma1"/>
		<histo:hasComponent rdf:resource="#Stroma1"/>
		<histo:displayName rdf:datatype="http://www.w3.org/2001/XMLSchema#string">Tumor Region Appearing a Glandular Pattern with Apoptotic Bodies</histo:displayName>
		<histo:hasXref rdf:resource="#UnificationXref_Tumor_Tissue"/>
	</histo:Tumor>
	<histo:Parenchyma rdf:ID="Parenchyma1">
		<histo:hasAnatomicalEntity rdf:resource="#Vesicle1"/>
		<histo:hasAnatomicalEntity rdf:resource="#Vesicle2"/>
		<histo:hasAnatomicalEntity rdf:resource="#Vesicle3"/>
        <histo:hasAnatomicalEntity rdf:resource="#Cavity1"/>
		<histo:displayName rdf:datatype="http://www.w3.org/2001/XMLSchema#string">Parenchyma of Tumor Region</histo:displayName>
		<histo:hasXref rdf:resource="#UnificationXref_Tumor_Parenchyma"/>
	</histo:Parenchyma>
	<histo:Stroma rdf:ID="Stroma1">
		<histo:displayName rdf:datatype="http://www.w3.org/2001/XMLSchema#string">Stroma of Tumor Region</histo:displayName>
		<histo:hasXref rdf:resource="#UnificationXref_Tumor_Stroma"/>
	</histo:Stroma>
    <histo:Tumor rdf:ID="Tumor2">
		<histo:hasComponent rdf:resource="#Parenchyma2"/>
		<histo:hasComponent rdf:resource="#Stroma2"/>
		<histo:displayName rdf:datatype="http://www.w3.org/2001/XMLSchema#string">Tumor Region Appearing a Glandular Pattern with Apical Mitoses</histo:displayName>
		<histo:hasXref rdf:resource="#UnificationXref_Tumor_Tissue"/>
	</histo:Tumor>
	<histo:Parenchyma rdf:ID="Parenchyma2">
		<histo:hasAnatomicalEntity rdf:resource="#Tumor_Cell1"/>
		<histo:hasAnatomicalEntity rdf:resource="#Tumor_Cell2"/>
		<histo:hasAnatomicalEntity rdf:resource="#Tumor_Cell3"/>
        <histo:hasAnatomicalEntity rdf:resource="#Cavity2"/>
		<histo:displayName rdf:datatype="http://www.w3.org/2001/XMLSchema#string">Parenchyma of Tumor Region</histo:displayName>
		<histo:hasXref rdf:resource="#UnificationXref_Tumor_Parenchyma"/>
	</histo:Parenchyma>
	<histo:Stroma rdf:ID="Stroma2">
		<histo:displayName rdf:datatype="http://www.w3.org/2001/XMLSchema#string">Stroma of Tumor Region</histo:displayName>
		<histo:hasXref rdf:resource="#UnificationXref_Tumor_Stroma"/>
	</histo:Stroma>

    
    <!--Cell -->
    <histo:NeoplasticCell rdf:ID="Tumor_Cell1">
		<histo:hasCellularComponent rdf:resource="#Mitotic_chromosome1"/>
		<histo:entityReference rdf:resource="#CellReference_Cell"/>
		<histo:displayName rdf:datatype="http://www.w3.org/2001/XMLSchema#string">Tumor Cell</histo:displayName>
		<histo:hasXref rdf:resource="#UnificationXref_Neoplastic_Cell"/>
	</histo:NeoplasticCell>
	<histo:NeoplasticCell rdf:ID="Tumor_Cell2">
		<histo:hasCellularComponent rdf:resource="#Mitotic_chromosome2"/>
		<histo:entityReference rdf:resource="#CellReference_Cell"/>
		<histo:displayName rdf:datatype="http://www.w3.org/2001/XMLSchema#string">Tumor Cell</histo:displayName>
		<histo:hasXref rdf:resource="#UnificationXref_Neoplastic_Cell"/>
	</histo:NeoplasticCell>
    <histo:NeoplasticCell rdf:ID="Tumor_Cell3">
		<histo:hasCellularComponent rdf:resource="#Mitotic_chromosome3"/>
		<histo:entityReference rdf:resource="#CellReference_Cell"/>
		<histo:displayName rdf:datatype="http://www.w3.org/2001/XMLSchema#string">Tumor Cell</histo:displayName>
		<histo:hasXref rdf:resource="#UnificationXref_Neoplastic_Cell"/>
	</histo:NeoplasticCell>
    <histo:NeoplasticCell rdf:ID="Tumor_Cell4">
		<histo:entityReference rdf:resource="#CellReference_Cell"/>
        <histo:hasAttribute rdf:resource="#EntityAttribute_Necrotic"/>
		<histo:displayName rdf:datatype="http://www.w3.org/2001/XMLSchema#string">Necrotic tumor Cell</histo:displayName>
		<histo:hasXref rdf:resource="#UnificationXref_Neoplastic_Cell"/>
	</histo:NeoplasticCell>
	<histo:NeoplasticCell rdf:ID="Tumor_Cell5">
		<histo:entityReference rdf:resource="#CellReference_Cell"/>
        <histo:hasAttribute rdf:resource="#EntityAttribute_Necrotic"/>
		<histo:displayName rdf:datatype="http://www.w3.org/2001/XMLSchema#string">Necrotic tumor Cell</histo:displayName>
		<histo:hasXref rdf:resource="#UnificationXref_Neoplastic_Cell"/>
	</histo:NeoplasticCell>
    <histo:NeoplasticCell rdf:ID="Tumor_Cell6">
		<histo:entityReference rdf:resource="#CellReference_Cell"/>
        <histo:hasAttribute rdf:resource="#EntityAttribute_Necrotic"/>
		<histo:displayName rdf:datatype="http://www.w3.org/2001/XMLSchema#string">Necrotic tumor Cell</histo:displayName>
		<histo:hasXref rdf:resource="#UnificationXref_Neoplastic_Cell"/>
	</histo:NeoplasticCell>


    <!--Chromosome -->
	<histo:NeoplasticCellularComponent rdf:ID="Mitotic_chromosome1">
		<histo:entityReference rdf:resource="#CellularComponentReference_Chromosome"/>
		<histo:displayName rdf:datatype="http://www.w3.org/2001/XMLSchema#string">Mitotic Chromosome</histo:displayName>
	</histo:NeoplasticCellularComponent>
	<histo:NeoplasticCellularComponent rdf:ID="Mitotic_chromosome2">
		<histo:entityReference rdf:resource="#CellularComponentReference_Chromosome"/>
		<histo:displayName rdf:datatype="http://www.w3.org/2001/XMLSchema#string">Mitotic Chromosome</histo:displayName>
	</histo:NeoplasticCellularComponent>
	<histo:NeoplasticCellularComponent rdf:ID="Mitotic_chromosome3">
		<histo:entityReference rdf:resource="#CellularComponentReference_Chromosome"/>
		<histo:displayName rdf:datatype="http://www.w3.org/2001/XMLSchema#string">Mitotic Chromosome</histo:displayName>
	</histo:NeoplasticCellularComponent>


    <!--Vesicle -->
    <histo:Other_ParenchymaEntity rdf:ID="Vesicle1">
		<histo:hasCell rdf:resource="#Tumor_Cell4"/>
		<histo:entityReference rdf:resource="#AnatomicalEntityReference_Vesicle"/>
		<histo:displayName rdf:datatype="http://www.w3.org/2001/XMLSchema#string">Apoptotic Body</histo:displayName>
        <histo:comment rdf:datatype="http://www.w3.org/2001/XMLSchema#string">A vesicle containing parts of a dying cell</histo:comment>
		<histo:hasXref rdf:resource="#UnificationXref_Apoptotic_Body"/>
	</histo:Other_ParenchymaEntity>
    <histo:Other_ParenchymaEntity rdf:ID="Vesicle2">
		<histo:hasCell rdf:resource="#Tumor_Cell5"/>
		<histo:entityReference rdf:resource="#AnatomicalEntityReference_Vesicle"/>
		<histo:displayName rdf:datatype="http://www.w3.org/2001/XMLSchema#string">Apoptotic Body</histo:displayName>
        <histo:comment rdf:datatype="http://www.w3.org/2001/XMLSchema#string">A vesicle containing parts of a dying cell</histo:comment>
		<histo:hasXref rdf:resource="#UnificationXref_Apoptotic_Body"/>
	</histo:Other_ParenchymaEntity>
    <histo:Other_ParenchymaEntity rdf:ID="Vesicle3">
		<histo:hasCell rdf:resource="#Tumor_Cell6"/>
		<histo:entityReference rdf:resource="#AnatomicalEntityReference_Vesicle"/>
		<histo:displayName rdf:datatype="http://www.w3.org/2001/XMLSchema#string">Apoptotic Body</histo:displayName>
        <histo:comment rdf:datatype="http://www.w3.org/2001/XMLSchema#string">A vesicle containing parts of a dying cell</histo:comment>
		<histo:hasXref rdf:resource="#UnificationXref_Apoptotic_Body"/>
	</histo:Other_ParenchymaEntity>


    <!--Cavity -->
    <histo:Other_ParenchymaEntity rdf:ID="Cavity1">
        <histo:entityReference rdf:resource="#AnatomicalEntityReference_Cavity"/>
    </histo:Other_ParenchymaEntity>
    <histo:Other_ParenchymaEntity rdf:ID="Cavity2">
        <histo:entityReference rdf:resource="#AnatomicalEntityReference_Cavity"/>
    </histo:Other_ParenchymaEntity>

    <!--EntityReference -->
	<histo:CellReference rdf:ID="CellReference_Cell">
        <histo:hasXref rdf:resource="#UnificationXref_Cell"/>
		<histo:displayName rdf:datatype="http://www.w3.org/2001/XMLSchema#string">Cell</histo:displayName>
    </histo:CellReference>
	<histo:CellularComponentReference rdf:ID="CellularComponentReference_Chromosome">
        <histo:hasXref rdf:resource="#UnificationXref_Chromosome"/>
		<histo:displayName rdf:datatype="http://www.w3.org/2001/XMLSchema#string">Chromosome</histo:displayName>
    </histo:CellularComponentReference>
	<histo:Other_AnatomicalEntityReference rdf:ID="AnatomicalEntityReference_Vesicle">
        <histo:hasXref rdf:resource="#UnificationXref_Vesicle"/>
		<histo:displayName rdf:datatype="http://www.w3.org/2001/XMLSchema#string" >Vesicle</histo:displayName>
    </histo:Other_AnatomicalEntityReference>
    <histo:Other_AnatomicalEntityReference rdf:ID="AnatomicalEntityReference_Cavity">
        <histo:hasXref rdf:resource="#UnificationXref_Anatomical_Cavity"/>
        <histo:displayName rdf:datatype="http://www.w3.org/2001/XMLSchema#string" >Cavity</histo:displayName>
    </histo:Other_AnatomicalEntityReference>


	<!--EntityAttribute -->
	<histo:EntityAttribute rdf:ID="EntityAttribute_Necrotic">
        <histo:hasXref rdf:resource="#UnificationXref_Necrotic"/>
		<histo:displayName rdf:datatype="http://www.w3.org/2001/XMLSchema#string">Necrotic</histo:displayName>
		<histo:comment rdf:datatype="http://www.w3.org/2001/XMLSchema#string">Undergoing unprogrammed cell death.</histo:comment>
    </histo:EntityAttribute>    

    
    <!--Xref -->
    <histo:UnificationXref rdf:ID="UnificationXref_Cervical_Adenocarcinoma">
        <histo:uri rdf:datatype="http://www.w3.org/2001/XMLSchema#string">http://purl.obolibrary.org/obo/NCIT_C4029</histo:uri>
    </histo:UnificationXref> 
    <histo:UnificationXref rdf:ID="UnificationXref_HPVA">
        <histo:uri rdf:datatype="http://www.w3.org/2001/XMLSchema#string">http://purl.obolibrary.org/obo/NCIT_C27677</histo:uri>
    </histo:UnificationXref> 
    <histo:UnificationXref rdf:ID="UnificationXref_HPVA_Usual_Type">
        <histo:uri rdf:datatype="http://www.w3.org/2001/XMLSchema#string">http://www.aipath.com/histo/TPO_0000008</histo:uri>
    </histo:UnificationXref>
    <histo:UnificationXref rdf:ID="UnificationXref_Tumor_Tissue">
        <histo:uri rdf:datatype="http://www.w3.org/2001/XMLSchema#string">http://purl.obolibrary.org/obo/NCIT_C18009</histo:uri>
    </histo:UnificationXref>
	<histo:UnificationXref rdf:ID="UnificationXref_Tumor_Parenchyma">
        <histo:uri rdf:datatype="http://www.w3.org/2001/XMLSchema#string">http://www.aipath.com/histo/HISTO_0000001</histo:uri>
    </histo:UnificationXref>
	<histo:UnificationXref rdf:ID="UnificationXref_Tumor_Stroma">
        <histo:uri rdf:datatype="http://www.w3.org/2001/XMLSchema#string">http://www.aipath.com/histo/HISTO_0000002</histo:uri>
    </histo:UnificationXref> 
    <histo:UnificationXref rdf:ID="UnificationXref_Anatomical_Cavity">
        <histo:uri rdf:datatype="http://www.w3.org/2001/XMLSchema#string">http://purl.obolibrary.org/obo/FMA_67552</histo:uri>
    </histo:UnificationXref>
    <histo:UnificationXref rdf:ID="UnificationXref_Cell">
        <histo:uri rdf:datatype="http://www.w3.org/2001/XMLSchema#string">http://purl.obolibrary.org/obo/FMA_68646</histo:uri>
    </histo:UnificationXref>
	<histo:UnificationXref rdf:ID="UnificationXref_Vesicle">
        <histo:uri rdf:datatype="http://www.w3.org/2001/XMLSchema#string">http://purl.obolibrary.org/obo/GO_0031982</histo:uri>
    </histo:UnificationXref>
    <histo:UnificationXref rdf:ID="UnificationXref_Apoptotic_Body">
        <histo:uri rdf:datatype="http://www.w3.org/2001/XMLSchema#string">http://purl.obolibrary.org/obo/GO_0097189</histo:uri>
    </histo:UnificationXref>
	<histo:UnificationXref rdf:ID="UnificationXref_Chromosome">
        <histo:uri rdf:datatype="http://www.w3.org/2001/XMLSchema#string">http://purl.obolibrary.org/obo/GO_0005694</histo:uri>
    </histo:UnificationXref>
    <histo:UnificationXref rdf:ID="UnificationXref_Neoplastic_Cell">
        <histo:uri rdf:datatype="http://www.w3.org/2001/XMLSchema#string">http://purl.obolibrary.org/obo/NCIT_C12922</histo:uri>
    </histo:UnificationXref>
    <histo:UnificationXref rdf:ID="UnificationXref_Glandular_Pattern">
        <histo:uri rdf:datatype="http://www.w3.org/2001/XMLSchema#string">http://purl.obolibrary.org/obo/NCIT_C35929</histo:uri>
    </histo:UnificationXref>
    <histo:UnificationXref rdf:ID="UnificationXref_Glandular_Pattern_with_Apical_Mitoses">
        <histo:uri rdf:datatype="http://www.w3.org/2001/XMLSchema#string">http://www.aipath.com/histo/HISTO_0000009</histo:uri>
    </histo:UnificationXref>   
    <histo:UnificationXref rdf:ID="UnificationXref_Glandular_Pattern_with_Apoptic_Bodies">
        <histo:uri rdf:datatype="http://www.w3.org/2001/XMLSchema#string">http://www.aipath.com/histo/HISTO_0000010</histo:uri>
    </histo:UnificationXref>
    <histo:UnificationXref rdf:ID="UnificationXref_Mitoses">
        <histo:uri rdf:datatype="http://www.w3.org/2001/XMLSchema#string">http://www.ebi.ac.uk/cmpo/CMPO_0000219</histo:uri>
    </histo:UnificationXref> 
    <histo:UnificationXref rdf:ID="UnificationXref_Apoptotic_Cell_Phenotype">
        <histo:uri rdf:datatype="http://www.w3.org/2001/XMLSchema#string">http://www.ebi.ac.uk/cmpo/CMPO_0000048</histo:uri>
    </histo:UnificationXref> 
    <histo:UnificationXref rdf:ID="UnificationXref_Necrotic">
        <histo:uri rdf:datatype="http://www.w3.org/2001/XMLSchema#string">http://purl.obolibrary.org/obo/PATO_0000647</histo:uri>
    </histo:UnificationXref>
    <histo:UnificationXref rdf:ID="UnificationXref_Percent_of_Tumor_Having_Cells_with_Mucinous_Cytoplasm">
        <histo:uri rdf:datatype="http://www.w3.org/2001/XMLSchema#string">http://www.aipath.com/histo/HISTO_0000011</histo:uri>
    </histo:UnificationXref>
    <histo:PublicationXref rdf:ID="PublicationXref_WHO2020">
        <histo:id rdf:datatype="http://www.w3.org/2001/XMLSchema#string">9283245040</histo:id>
        <histo:db rdf:datatype="http://www.w3.org/2001/XMLSchema#string">ISBN</histo:db>
        <histo:year rdf:datatype="http://www.w3.org/2001/XMLSchema#int">2020</histo:year>
        <histo:title rdf:datatype="http://www.w3.org/2001/XMLSchema#string">Female Genital Tumours: WHO Classification of Tumours (Medicine) 5th Edition</histo:title>
        <histo:author rdf:datatype="http://www.w3.org/2001/XMLSchema#string">WHO Classification of Tumours Editorial Board</histo:author>
    </histo:PublicationXref>
	<histo:Diagnosis rdf:ID="Diagnosis">
		<histo:hasXref rdf:resource="#UnificationXref_Diagnosis"/>
		<histo:has_Quantitative_Metric_Evidence rdf:resource="#Quantitative_Metric1"/>
		<histo:has_Morphologic_Evidence rdf:resource="#Glandular_Pattern7"/>
		<histo:has_Morphologic_Evidence rdf:resource="#Glandular_Pattern6"/>
		<histo:has_Morphologic_Evidence rdf:resource="#Glandular_Pattern5"/>
		<histo:has_Morphologic_Evidence rdf:resource="#Glandular_Pattern4"/>
		<histo:has_Morphologic_Evidence rdf:resource="#Glandular_Pattern3"/>
		<histo:has_Morphologic_Evidence rdf:resource="#Glandular_Pattern2"/>
		<histo:has_Morphologic_Evidence rdf:resource="#Glandular_Pattern1"/>
	</histo:Diagnosis>
	<histo:UnificationXref rdf:ID="UnificationXref_Diagnosis">
		<histo:uri>http://www.aipath.com/histo/TPO_0000008</histo:uri>
	</histo:UnificationXref>
</rdf:RDF>
